kerasvis/__init__.py
kerasvis/callback.py
kerasvis/runserver.py
kerasvis/server/__init__.py
kerasvis/server/dataloader.py
kerasvis/server/main.py
kerasvis/server/plots.py
kerasvis/server/static/styles/style.css
kerasvis/server/templates/base.html
kerasvis/server/templates/detail.html
kerasvis/server/templates/idnotfound.html
kerasvis/server/templates/nodb.html
kerasvis/server/templates/overview.html
kerasvis-0.4.3.dist-info/DESCRIPTION.rst
kerasvis-0.4.3.dist-info/METADATA
kerasvis-0.4.3.dist-info/RECORD
kerasvis-0.4.3.dist-info/WHEEL
kerasvis-0.4.3.dist-info/metadata.json
kerasvis-0.4.3.dist-info/top_level.txt
