Metadata-Version: 2.0
Name: kerasvis
Version: 0.4.3
Summary: Visualize Keras optimizations live in your browser
Home-page: http://github.com/neuralyzer/kerasvis
Author: Emmanuel Klinger
Author-email: emmanuel.klinger@gmail.com
License: GPL
Keywords: keras optimization visualization
Platform: UNKNOWN
Requires-Dist: SQLAlchemy
Requires-Dist: bokeh
Requires-Dist: flask
Requires-Dist: pandas
